<?xml version="1.0" encoding="utf-8"?>
<GameData>
  <EnglishText>
    <Row Tag="LOC_POLAND_JADWIGA_MOD_TITLE">
      <Text>Пакет цивілізації Польща</Text>
    </Row>
    <Row Tag="LOC_POLAND_JADWIGA_MOD_TEASER">
      <Text>Нова цивілізація та лідер - Ядвіга Польська</Text>
    </Row>
    <Row Tag="LOC_POLAND_JADWIGA_MOD_DESCRIPTION">
      <Text>Містить нову цивілізацію та лідера.</Text>
    </Row>
    <Row Tag="LOC_MOD_POLAND_SCENARIO_TITLE">
      <Text>Сценарій: Спадок Ядвіги</Text>
    </Row>
    <Row Tag="LOC_MOD_POLAND_SCENARIO_TEASER">
      <Text>Боріться разом з двома іншими гравцями, щоб захистити Польщу від іноземних нашестів.</Text>
    </Row>
    <Row Tag="LOC_MOD_POLAND_SCENARIO_DESCRIPTION">
      <Text>У цьому сценарії з 60 поворотів ви стоїте на хрестовині Європи, захищаючи родючі польські землі від постійних нападів загарбників з усіх напрямків. Зібрайте своїх Крилатих гусарів і протиставтеся Тевтонським лицарям та Османським туркам, розвиваючи свою цивілізацію. [NEWLINE][NEWLINE]Переможцем є гравець з найкращою імперією за стандартним підрахунком очок в кінці гри.</Text>
    </Row>
  </EnglishText>
</GameData>