<?xml version="1.0" encoding="utf-8"?>
<GameData>
  <EnglishText>
    <Row Tag="LOC_BYZANTIUM_GAUL_MOD_TITLE">
      <Text>Bysantti ja Gallia-pakkaus</Text>
    </Row>
    <Row Tag="LOC_BYZANTIUM_GAUL_MOD_TEASER">
      <Text>Uudet sivilisaatiot ja johtajat - Basil II Bysantista ja Ambiorix Gaulista</Text>
    </Row>
    <Row Tag="LOC_BYZANTIUM_GAUL_MOD_DESCRIPTION">
      <Text>Sisältää kaksi uutta sivilisaatiota ja johtajaa, 2 uutta maailmanihmettä, 1 uuden karttakomennon ja Dramatic Ages -pelitilan.</Text>
    </Row>
  </EnglishText>
</GameData>