<?xml version="1.0" encoding="utf-8" standalone="yes"?>
<GameData>
  <EnglishText>
    <!-- Scenario Package -->
    <Row Tag="LOC_CIV_ROYALE_MOD_TITLE">
      <Text>Moninpelitilanne: Punainen Kuolema (Taistelu Royale)</Text>
    </Row>
    <Row Tag="LOC_CIV_ROYALE_MOD_TEASER">
      <Text>Tässä moninpeliskenaariossa sinun täytyy selviytyä muista ryhmistä, jotka taistelevat tilasta viimeisellä siirtokunnan laivalla, sekä itse planeetasta. Kierrosten kesto vaihtelee yleensä 20-45 minuutin välillä pelin koosta riippuen.</Text>
    </Row>
    <Row Tag="LOC_CIV_ROYALE_MOD_DESCRIPTION_BASIC">
      <Text>Johtajamme ovat pettäneet meidät. Punainen kuolema tulee kaikkien luokse. Vanha sivilisaatiomme ei kestänyt ajan testiä. [NEWLINE][NEWLINE]Ainoa toivomme on yhdessä avaruusaluksessa, joka odottaa kiertoradalla tämän maailman viimeisiä selviytyjiä. Voimme ohjata laskeutujaa etänä, mutta muut ryhmittymät häiritsevät signaalia. Ainoa tapa selviytyä on eliminoida muut ryhmittymät. [NEWLINE][NEWLINE]Tervetuloa tämän maailman viimeiseen sivilisaatioon.</Text>
    </Row>
    <Row Tag="LOC_CIV_ROYALE_MOD_DESCRIPTION_TUTORIAL">
      <Text>Johtajamme ovat pettäneet meidät. Punainen kuolema tulee meidän kaikkien luokse. Vanha sivilisaatiomme ei kestänyt ajan testiä. [NEWLINE] [NEWLINE] Ainoa toivomme on yhdessä kolonialaiva, joka odottaa kiertoradalla tämän maailman viimeisiä selviytyjiä. Voimme ohjata laskeutujaa etänä, mutta muut ryhmittymät häiritsevät signaaliasi. Ainoa tapa, jolla selviämme, on poistaa muut ryhmittymät. [NEWLINE] [NEWLINE] Tervetuloa tämän maailman viimeiseen sivilisaatioon.</Text>
    </Row>
  </EnglishText>
</GameData>